json2tsv/__init__.py
json2tsv/json2tsv.py
json2tsv/tsv2json.py
json2tsv/util.py
json2tsv-0.1.2.dist-info/DESCRIPTION.rst
json2tsv-0.1.2.dist-info/entry_points.txt
json2tsv-0.1.2.dist-info/METADATA
json2tsv-0.1.2.dist-info/metadata.json
json2tsv-0.1.2.dist-info/RECORD
json2tsv-0.1.2.dist-info/top_level.txt
json2tsv-0.1.2.dist-info/WHEEL
