Metadata-Version: 2.0
Name: json2tsv
Version: 0.1.2
Summary: Convert json to tab-separated format.
Home-page: https://github.com/aronwc/json2tsv
Author: Aron Culotta
Author-email: aronwc@gmail.com
License: BSD
Keywords: json2tsv
Platform: UNKNOWN
Classifier: Development Status :: 2 - Pre-Alpha
Classifier: Intended Audience :: Developers
Classifier: License :: OSI Approved :: BSD License
Classifier: Natural Language :: English
Classifier: Programming Language :: Python :: 2
Classifier: Programming Language :: Python :: 2.6
Classifier: Programming Language :: Python :: 2.7
Classifier: Programming Language :: Python :: 3
Classifier: Programming Language :: Python :: 3.3
